{"place_id":"50279371","licence":"Data © OpenStreetMap contributors, ODbL 1.0. http:\/\/www.openstreetmap.org\/copyright","osm_type":"node","osm_id":"3645919852","lat":"28.4697155","lon":"-16.2484751","display_name":"Kimpira, 5, Plaza Isabel II, El Toscal, Centro-Ifara, Santa Cruz de Tenerife, Canarias, 38002, España","address":{"restaurant":"Kimpira","house_number":"5","pedestrian":"Plaza Isabel II","suburb":"El Toscal","city_district":"Centro-Ifara","city":"Santa Cruz de Tenerife","county":"Santa Cruz de Tenerife","state":"Canarias","postcode":"38002","country":"España","country_code":"es"},"boundingbox":["28.4696155","28.4698155","-16.2485751","-16.2483751"]}
